AUTHORS.rst
HISTORY.rst
LICENSE
MANIFEST.in
README.rst
requirements.txt
setup.cfg
setup.py
versioneer.py
docs/Makefile
docs/authors.rst
docs/cli_docs.rst
docs/conf.py
docs/history.rst
docs/index.rst
docs/license.rst
docs/make.bat
requirements/base.txt
requirements/develop.txt
requirements/test.txt
requirements/test_black.txt
sodar_cli/__init__.py
sodar_cli/__main__.py
sodar_cli/_version.py
sodar_cli/common.py
sodar_cli/exceptions.py
sodar_cli.egg-info/PKG-INFO
sodar_cli.egg-info/SOURCES.txt
sodar_cli.egg-info/dependency_links.txt
sodar_cli.egg-info/entry_points.txt
sodar_cli.egg-info/not-zip-safe
sodar_cli.egg-info/requires.txt
sodar_cli.egg-info/top_level.txt
sodar_cli/api/__init__.py
sodar_cli/api/landingzone.py
sodar_cli/api/models.py
sodar_cli/api/project.py
sodar_cli/api/samplesheet.py
sodar_cli/landingzone/__init__.py
sodar_cli/landingzone/config.py
sodar_cli/landingzone/create.py
sodar_cli/landingzone/list.py
sodar_cli/landingzone/move.py
sodar_cli/landingzone/retrieve.py
sodar_cli/landingzone/validate.py
sodar_cli/project/__init__.py
sodar_cli/project/config.py
sodar_cli/project/create.py
sodar_cli/project/list.py
sodar_cli/project/retrieve.py
sodar_cli/project/update.py
sodar_cli/samplesheet/__init__.py
sodar_cli/samplesheet/config.py
sodar_cli/samplesheet/export.py
sodar_cli/samplesheet/importisa.py
sodar_cli/samplesheet/retrieve.py
tests/__init__.py
tests/factories.py
tests/test_api_landingzone.py
tests/test_api_project.py
tests/test_api_samplesheet.py
tests/test_import.py
tests/test_landingzone.py
tests/test_main.py
tests/test_project.py
tests/test_samplesheet.py
tests/data/config/sodarrc.toml
tests/data/isatab/a_test_exome_sequencing_nucleotide_sequencing.txt
tests/data/isatab/i_Investigation.txt
tests/data/isatab/s_test.txt