Metadata-Version: 1.1
Name: sodar-cli
Version: 0.1.0
Summary: Command line interface client for SODAR REST API.
Home-page: https://github.com/bihealth/sodar-cli
Author: Manuel Holtgrewe
Author-email: manuel.holtgrewe@bihealth.de
License: MIT license
Keywords: sodar_cli
Platform: UNKNOWN
Classifier: Development Status :: 4 - Beta
Classifier: Intended Audience :: Developers
Classifier: License :: OSI Approved :: MIT License
Classifier: Natural Language :: English
Classifier: Topic :: Scientific/Engineering :: Bio-Informatics
Classifier: Programming Language :: Python :: 3
Classifier: Programming Language :: Python :: 3.6
Classifier: Programming Language :: Python :: 3.7
Classifier: Programming Language :: Python :: 3.8
